ydl/__init__.py
ydl/__main__.py
ydl/_core.py
ydl/_header.py
ydl_ipc-0.2.0.dist-info/LICENSE
ydl_ipc-0.2.0.dist-info/METADATA
ydl_ipc-0.2.0.dist-info/WHEEL
ydl_ipc-0.2.0.dist-info/RECORD
